syft_hub/__init__.py
syft_hub/main.py
syft_hub/cli/__init__.py
syft_hub/cli/commands.py
syft_hub/cli/display.py
syft_hub/cli/main.py
syft_hub/clients/__init__.py
syft_hub/clients/accounting_client.py
syft_hub/clients/auth_client.py
syft_hub/clients/request_client.py
syft_hub/core/__init__.py
syft_hub/core/decorators.py
syft_hub/core/exceptions.py
syft_hub/core/pipeline.py
syft_hub/core/service.py
syft_hub/core/settings.py
syft_hub/core/types.py
syft_hub/discovery/__init__.py
syft_hub/discovery/filters.py
syft_hub/discovery/index.py
syft_hub/discovery/parser.py
syft_hub/discovery/scanner.py
syft_hub/models/__init__.py
syft_hub/models/builders.py
syft_hub/models/pipeline.py
syft_hub/models/requests.py
syft_hub/models/responses.py
syft_hub/models/service_info.py
syft_hub/models/services_list.py
syft_hub/models/validation.py
syft_hub/services/__init__.py
syft_hub/services/chat.py
syft_hub/services/health.py
syft_hub/services/search.py
syft_hub/utils/__init__.py
syft_hub/utils/async_utils.py
syft_hub/utils/caching.py
syft_hub/utils/constants.py
syft_hub/utils/estimator.py
syft_hub/utils/formatting.py
syft_hub/utils/logger.py
syft_hub/utils/spinner.py
syft_hub/utils/syftbox_services_widget.html
syft_hub/utils/theme.py
syft_hub/utils/validator.py
syft_hub/views/progress_widget.py
syft_hub/views/services_widget.py
syft_hub-0.1.30.dist-info/licenses/LICENSE
syft_hub-0.1.30.dist-info/METADATA
syft_hub-0.1.30.dist-info/WHEEL
syft_hub-0.1.30.dist-info/entry_points.txt
syft_hub-0.1.30.dist-info/top_level.txt
syft_hub-0.1.30.dist-info/RECORD
