Metadata-Version: 2.4
Name: syft-hub
Version: 0.1.30
Summary: Python SDK for discovering and using AI models across the SyftBox network
Author-email: SyftBox Team <info@openmined.org>, Irina B <irina@openmined.org>, Callis E <callis@openmined.org>
Maintainer-email: SyftBox Team <info@openmined.org>, Irina B <irina@openmined.org>, Callis E <callis@openmined.org>
License: MIT
Project-URL: Homepage, https://syftbox.openmined.org
Project-URL: Documentation, https://docs.syftbox.openmined.org/nsai-sdk
Project-URL: Repository, https://github.com/OpenMined/syftbox-nsai-sdk
Project-URL: Bug Tracker, https://github.com/OpenMined/syftbox-nsai-sdk/issues
Project-URL: Changelog, https://github.com/OpenMined/syftbox-nsai-sdk/blob/main/CHANGELOG.md
Requires-Python: >=3.9
License-File: LICENSE
Requires-Dist: httpx>=0.24.0
Requires-Dist: rich>=13.0.0
Requires-Dist: syft-core>=0.2.8
Requires-Dist: syft-rpc>=0.4.0
Requires-Dist: syft-crypto>=0.1.1
Requires-Dist: syft-accounting-sdk>=0.1.0
Requires-Dist: ipython==8.10.0
Requires-Dist: jinja2>=3.1.6
Requires-Dist: pydantic>=2.11.2
Requires-Dist: requests==2.32.4
Requires-Dist: click<9.0.0,>=8.1.8
Requires-Dist: sqlmodel>=0.0.24
Requires-Dist: typer>=0.15.2
Requires-Dist: cryptography>=41.0.5
Requires-Dist: python-dotenv>=1.1.0
Requires-Dist: pydantic-settings>=2.10.1
Requires-Dist: tabulate>=0.9.0
Requires-Dist: aiohttp>=3.8.0
Requires-Dist: colorama>=0.4.6
Requires-Dist: fastapi>=0.104.0
Requires-Dist: uvicorn>=0.24.0
Requires-Dist: markdown2>=2.5.4
Provides-Extra: installer
Requires-Dist: syft-installer>=0.9.1; extra == "installer"
Dynamic: license-file
